recipescraper.py
recipescraper-0.0.1.dist-info/LICENSE.txt
recipescraper-0.0.1.dist-info/METADATA
recipescraper-0.0.1.dist-info/WHEEL
recipescraper-0.0.1.dist-info/top_level.txt
recipescraper-0.0.1.dist-info/RECORD
