Metadata-Version: 2.2
Name: recipeScraper
Version: 0.0.1
Summary: A small example package
Author-email: Example Author <author@example.com>
License: 
Classifier: Programming Language :: Python :: 3
Classifier: Operating System :: OS Independent
Requires-Python: >=3.10
License-File: LICENSE.txt
Requires-Dist: requests>=2.32.3
Requires-Dist: beautifulsoup4>=4.12.3
Requires-Dist: pandas>=2.2.3
